{
  "id": 1404020,
  "home_team_score": 1,
  "away_team_score": 1,
  "date_time": "2024-02-18T13:00:00Z",
  "stadium": {
    "id": 228,
    "name": "Estadio de Vallecas",
    "city": "Madrid",
    "capacity": 14708
  },
  "home_team": {
    "id": 284,
    "name": "Rayo Vallecano",
    "short_name": "Rayo Vallecano",
    "acronym": "RAY"
  },
  "home_team_kit": {
    "id": 668,
    "team_id": 284,
    "season": {
      "id": 5,
      "start_year": 2018,
      "end_year": 2019,
      "name": "2018/2019"
    },
    "name": "Home",
    "jersey_color": "#ffffff",
    "number_color": "#b60000"
  },
  "away_team": {
    "id": 262,
    "name": "Real Madrid CF",
    "short_name": "Real Madrid",
    "acronym": "REA"
  },
  "away_team_kit": {
    "id": 159,
    "team_id": 262,
    "season": {
      "id": 4,
      "start_year": 2017,
      "end_year": 2018,
      "name": "2017/2018"
    },
    "name": "away",
    "jersey_color": "#000000",
    "number_color": "#ffffff"
  },
  "home_team_coach": {
    "id": 325,
    "first_name": "Andoni",
    "last_name": "Iraola"
  },
  "away_team_coach": {
    "id": 705,
    "first_name": "",
    "last_name": "Zinedine Zidane"
  },
  "competition_edition": {
    "id": 546,
    "competition": {
      "id": 4,
      "area": "ESP",
      "name": "LaLiga",
      "gender": "male",
      "age_group": "adult"
    },
    "season": {
      "id": 28,
      "start_year": 2023,
      "end_year": 2024,
      "name": "2023/2024"
    },
    "name": "ESP - LaLiga - 2023/2024"
  },
  "competition_round": {
    "id": 107,
    "name": "Round 25",
    "round_number": 25,
    "potential_overtime": false
  },
  "referees": [],
  "players": [
    {
      "player_role": {
        "id": 20,
        "position_group": "Full Back",
        "name": "Right Back",
        "acronym": "RB"
      },
      "start_time": "00:00:00",
      "end_time": null,
      "number": 20,
      "yellow_card": 1,
      "red_card": 0,
      "injured": false,
      "goal": 0,
      "own_goal": 0,
      "team_player_id": 92187,
      "team_id": 284,
      "id": 4518,
      "first_name": "Iván",
      "last_name": "Balliu Campeny",
      "short_name": "I. Balliu",
      "birthday": "1992-01-01",
      "trackable_object": 4528,
      "gender": "male"
    },
    {
      "player_role": {
        "id": 4,
        "position_group": "Central Defender",
        "name": "Right Center Back",
        "acronym": "RCB"
      },
      "start_time": "00:00:00",
      "end_time": null,
      "number": 18,
      "yellow_card": 0,
      "red_card": 0,
      "injured": false,
      "goal": 0,
      "own_goal": 0,
      "team_player_id": 248385,
      "team_id": 262,
      "id": 12218,
      "first_name": "Aurélien",
      "last_name": "Tchouaméni",
      "short_name": "A. Tchouaméni",
      "birthday": "2000-01-27",
      "trackable_object": 12361,
      "gender": "male"
    },
    {
      "player_role": {
        "id": 3,
        "position_group": "Central Defender",
        "name": "Left Center Back",
        "acronym": "LCB"
      },
      "start_time": "00:00:00",
      "end_time": null,
      "number": 24,
      "yellow_card": 0,
      "red_card": 0,
      "injured": false,
      "goal": 0,
      "own_goal": 0,
      "team_player_id": 247582,
      "team_id": 284,
      "id": 3504,
      "first_name": "Florian",
      "last_name": "Lejeune",
      "short_name": "F. Lejeune",
      "birthday": "1991-05-20",
      "trackable_object": 3514,
      "gender": "male"
    },
    {
      "player_role": {
        "id": 22,
        "position_group": "Midfield",
        "name": "Right Defensive Midfield",
        "acronym": "RDM"
      },
      "start_time": "00:00:00",
      "end_time": null,
      "number": 23,
      "yellow_card": 0,
      "red_card": 0,
      "injured": false,
      "goal": 0,
      "own_goal": 0,
      "team_player_id": 25580,
      "team_id": 284,
      "id": 25878,
      "first_name": "Óscar Valentín",
      "last_name": "Martín Luengo",
      "short_name": "Óscar Valentín",
      "birthday": "1994-08-20",
      "trackable_object": 26939,
      "gender": "male"
    },
    {
      "player_role": {
        "id": 19,
        "position_group": "Full Back",
        "name": "Left Back",
        "acronym": "LB"
      },
      "start_time": "00:00:00",
      "end_time": null,
      "number": 12,
      "yellow_card": 0,
      "red_card": 0,
      "injured": false,
      "goal": 0,
      "own_goal": 0,
      "team_player_id": 1078671,
      "team_id": 284,
      "id": 25909,
      "first_name": "Luis Alfonso",
      "last_name": "Espino García",
      "short_name": "A. Espino",
      "birthday": "1992-01-05",
      "trackable_object": 26973,
      "gender": "male"
    },
    {
      "player_role": {
        "id": 11,
        "position_group": "Midfield",
        "name": "Attacking Midfield",
        "acronym": "AM"
      },
      "start_time": "01:26:18",
      "end_time": null,
      "number": 24,
      "yellow_card": 0,
      "red_card": 0,
      "injured": false,
      "goal": 0,
      "own_goal": 0,
      "team_player_id": 1062967,
      "team_id": 262,
      "id": 44876,
      "first_name": "Arda",
      "last_name": "Güler",
      "short_name": "A. Güler",
      "birthday": "2005-02-25",
      "trackable_object": 46002,
      "gender": "male"
    },
    {
      "player_role": {
        "id": 4,
        "position_group": "Central Defender",
        "name": "Right Center Back",
        "acronym": "RCB"
      },
      "start_time": "00:00:00",
      "end_time": null,
      "number": 5,
      "yellow_card": 0,
      "red_card": 0,
      "injured": false,
      "goal": 0,
      "own_goal": 0,
      "team_player_id": 1078672,
      "team_id": 284,
      "id": 23782,
      "first_name": "Aridane",
      "last_name": "Hernández Umpiérrez",
      "short_name": "Aridane Hernández",
      "birthday": "1989-03-23",
      "trackable_object": 24735,
      "gender": "male"
    },
    {
      "player_role": {
        "id": 20,
        "position_group": "Full Back",
        "name": "Right Back",
        "acronym": "RB"
      },
      "start_time": "01:14:47",
      "end_time": "01:34:37",
      "number": 2,
      "yellow_card": 1,
      "red_card": 1,
      "injured": false,
      "goal": 0,
      "own_goal": 0,
      "team_player_id": 961,
      "team_id": 262,
      "id": 2189,
      "first_name": "Daniel",
      "last_name": "Carvajal Ramos",
      "short_name": "Dani Carvajal",
      "birthday": "1992-01-11",
      "trackable_object": 2199,
      "gender": "male"
    },
    {
      "player_role": {
        "id": 7,
        "position_group": "Midfield",
        "name": "Defensive Midfield",
        "acronym": "DM"
      },
      "start_time": "01:09:29",
      "end_time": null,
      "number": 8,
      "yellow_card": 0,
      "red_card": 0,
      "injured": false,
      "goal": 0,
      "own_goal": 0,
      "team_player_id": 3017,
      "team_id": 262,
      "id": 10520,
      "first_name": "Toni",
      "last_name": "Kroos",
      "short_name": "T. Kroos",
      "birthday": "1990-01-04",
      "trackable_object": 10530,
      "gender": "male"
    },
    {
      "player_role": {
        "id": 16,
        "position_group": "Wide Attacker",
        "name": "Right Forward",
        "acronym": "RF"
      },
      "start_time": "01:09:29",
      "end_time": null,
      "number": 11,
      "yellow_card": 0,
      "red_card": 0,
      "injured": false,
      "goal": 0,
      "own_goal": 0,
      "team_player_id": 21859,
      "team_id": 262,
      "id": 23903,
      "first_name": "Rodrygo",
      "last_name": "Silva de Goes",
      "short_name": "Rodrygo",
      "birthday": "2001-01-09",
      "trackable_object": 24861,
      "gender": "male"
    },
    {
      "player_role": {
        "id": 12,
        "position_group": "Wide Attacker",
        "name": "Left Winger",
        "acronym": "LW"
      },
      "start_time": "00:00:00",
      "end_time": "01:20:47",
      "number": 18,
      "yellow_card": 1,
      "red_card": 0,
      "injured": false,
      "goal": 0,
      "own_goal": 0,
      "team_player_id": 9393,
      "team_id": 284,
      "id": 640,
      "first_name": "Álvaro",
      "last_name": "García Rivera",
      "short_name": "Álvaro García",
      "birthday": "1992-10-27",
      "trackable_object": 650,
      "gender": "male"
    },
    {
      "player_role": {
        "id": 20,
        "position_group": "Full Back",
        "name": "Right Back",
        "acronym": "RB"
      },
      "start_time": "00:00:00",
      "end_time": "01:14:47",
      "number": 17,
      "yellow_card": 0,
      "red_card": 0,
      "injured": false,
      "goal": 0,
      "own_goal": 0,
      "team_player_id": 223,
      "team_id": 262,
      "id": 6373,
      "first_name": "Lucas",
      "last_name": "Vázquez Iglesias",
      "short_name": "Lucas Vázquez",
      "birthday": "1991-07-01",
      "trackable_object": 6383,
      "gender": "male"
    },
    {
      "player_role": {
        "id": 19,
        "position_group": "Full Back",
        "name": "Left Back",
        "acronym": "LB"
      },
      "start_time": "00:00:00",
      "end_time": null,
      "number": 20,
      "yellow_card": 0,
      "red_card": 0,
      "injured": false,
      "goal": 0,
      "own_goal": 0,
      "team_player_id": 1062965,
      "team_id": 262,
      "id": 31993,
      "first_name": "Francisco José",
      "last_name": "García Torres",
      "short_name": "Fran García",
      "birthday": "1999-08-14",
      "trackable_object": 33095,
      "gender": "male"
    },
    {
      "player_role": {
        "id": 13,
        "position_group": "Wide Attacker",
        "name": "Right Winger",
        "acronym": "RW"
      },
      "start_time": "00:55:58",
      "end_time": null,
      "number": 19,
      "yellow_card": 0,
      "red_card": 0,
      "injured": false,
      "goal": 0,
      "own_goal": 0,
      "team_player_id": 25581,
      "team_id": 284,
      "id": 24247,
      "first_name": "Jorge",
      "last_name": "De Frutos Sebastián",
      "short_name": "Jorge de Frutos",
      "birthday": "1997-02-20",
      "trackable_object": 25252,
      "gender": "male"
    },
    {
      "player_role": {
        "id": 10,
        "position_group": "Midfield",
        "name": "Right Midfield",
        "acronym": "RM"
      },
      "start_time": "00:00:00",
      "end_time": null,
      "number": 15,
      "yellow_card": 0,
      "red_card": 0,
      "injured": false,
      "goal": 0,
      "own_goal": 0,
      "team_player_id": 6673,
      "team_id": 262,
      "id": 12251,
      "first_name": "Federico Santiago",
      "last_name": "Valverde Dipetta",
      "short_name": "F. Valverde",
      "birthday": "1998-07-22",
      "trackable_object": 12395,
      "gender": "male"
    },
    {
      "player_role": {
        "id": 15,
        "position_group": "Center Forward",
        "name": "Center Forward",
        "acronym": "CF"
      },
      "start_time": "00:00:00",
      "end_time": null,
      "number": 14,
      "yellow_card": 0,
      "red_card": 0,
      "injured": false,
      "goal": 1,
      "own_goal": 0,
      "team_player_id": 1062968,
      "team_id": 262,
      "id": 5449,
      "first_name": "José Luis",
      "last_name": "Sanmartín Mato",
      "short_name": "Joselu",
      "birthday": "1990-03-27",
      "trackable_object": 5459,
      "gender": "male"
    },
    {
      "player_role": {
        "id": 3,
        "position_group": "Central Defender",
        "name": "Left Center Back",
        "acronym": "LCB"
      },
      "start_time": "00:00:00",
      "end_time": null,
      "number": 6,
      "yellow_card": 0,
      "red_card": 0,
      "injured": false,
      "goal": 0,
      "own_goal": 0,
      "team_player_id": 3940,
      "team_id": 262,
      "id": 7840,
      "first_name": "José Ignacio",
      "last_name": "Fernández Iglesias",
      "short_name": "Nacho Fernández",
      "birthday": "1990-01-18",
      "trackable_object": 7850,
      "gender": "male"
    },
    {
      "player_role": {
        "id": 14,
        "position_group": "Wide Attacker",
        "name": "Left Forward",
        "acronym": "LF"
      },
      "start_time": "00:00:00",
      "end_time": null,
      "number": 7,
      "yellow_card": 0,
      "red_card": 0,
      "injured": false,
      "goal": 0,
      "own_goal": 0,
      "team_player_id": 6675,
      "team_id": 262,
      "id": 12253,
      "first_name": "Vinícius José",
      "last_name": "Paixão de Oliveira Júnior",
      "short_name": "Vinícius Júnior",
      "birthday": "2000-07-12",
      "trackable_object": 12397,
      "gender": "male"
    },
    {
      "player_role": {
        "id": 11,
        "position_group": "Midfield",
        "name": "Attacking Midfield",
        "acronym": "AM"
      },
      "start_time": "01:03:23",
      "end_time": null,
      "number": 14,
      "yellow_card": 0,
      "red_card": 0,
      "injured": false,
      "goal": 0,
      "own_goal": 0,
      "team_player_id": 1095501,
      "team_id": 284,
      "id": 34473,
      "first_name": "Enrique",
      "last_name": "Pérez Muñoz",
      "short_name": "Kike Pérez",
      "birthday": "1997-02-14",
      "trackable_object": 35585,
      "gender": "male"
    },
    {
      "player_role": {
        "id": 13,
        "position_group": "Wide Attacker",
        "name": "Right Winger",
        "acronym": "RW"
      },
      "start_time": "00:00:00",
      "end_time": "00:55:58",
      "number": 7,
      "yellow_card": 1,
      "red_card": 0,
      "injured": false,
      "goal": 0,
      "own_goal": 0,
      "team_player_id": 25599,
      "team_id": 284,
      "id": 25892,
      "first_name": "Isaac",
      "last_name": "Palazón Camacho",
      "short_name": "Isi Palazón",
      "birthday": "1994-12-27",
      "trackable_object": 26955,
      "gender": "male"
    },
    {
      "player_role": {
        "id": 7,
        "position_group": "Midfield",
        "name": "Defensive Midfield",
        "acronym": "DM"
      },
      "start_time": "00:00:00",
      "end_time": "01:09:29",
      "number": 12,
      "yellow_card": 1,
      "red_card": 0,
      "injured": false,
      "goal": 0,
      "own_goal": 0,
      "team_player_id": 100630,
      "team_id": 262,
      "id": 22103,
      "first_name": "Eduardo",
      "last_name": "Camavinga",
      "short_name": "E. Camavinga",
      "birthday": "2002-11-10",
      "trackable_object": 22340,
      "gender": "male"
    },
    {
      "player_role": {
        "id": 16,
        "position_group": "Wide Attacker",
        "name": "Right Forward",
        "acronym": "RF"
      },
      "start_time": "00:00:00",
      "end_time": "01:09:29",
      "number": 21,
      "yellow_card": 0,
      "red_card": 0,
      "injured": false,
      "goal": 0,
      "own_goal": 0,
      "team_player_id": 18355,
      "team_id": 262,
      "id": 11592,
      "first_name": "Brahim",
      "last_name": "Abdelkader Diaz",
      "short_name": "Brahim Diaz",
      "birthday": "1999-08-03",
      "trackable_object": 11673,
      "gender": "male"
    },
    {
      "player_role": {
        "id": 21,
        "position_group": "Midfield",
        "name": "Left Defensive Midfield",
        "acronym": "LDM"
      },
      "start_time": "01:03:23",
      "end_time": null,
      "number": 15,
      "yellow_card": 0,
      "red_card": 0,
      "injured": false,
      "goal": 0,
      "own_goal": 0,
      "team_player_id": 1232328,
      "team_id": 284,
      "id": 61905,
      "first_name": "Miguel ",
      "last_name": "Crespo da Silva",
      "short_name": "Miguel Crespo",
      "birthday": "1996-09-11",
      "trackable_object": 63031,
      "gender": "male"
    },
    {
      "player_role": {
        "id": 21,
        "position_group": "Midfield",
        "name": "Left Defensive Midfield",
        "acronym": "LDM"
      },
      "start_time": "00:00:00",
      "end_time": "01:03:23",
      "number": 17,
      "yellow_card": 0,
      "red_card": 0,
      "injured": false,
      "goal": 0,
      "own_goal": 0,
      "team_player_id": 100040,
      "team_id": 284,
      "id": 10590,
      "first_name": "Unai",
      "last_name": "López Cabrera",
      "short_name": "Unai López",
      "birthday": "1995-10-30",
      "trackable_object": 10600,
      "gender": "male"
    },
    {
      "player_role": {
        "id": 9,
        "position_group": "Midfield",
        "name": "Left Midfield",
        "acronym": "LM"
      },
      "start_time": "00:00:00",
      "end_time": "01:26:18",
      "number": 10,
      "yellow_card": 0,
      "red_card": 0,
      "injured": false,
      "goal": 0,
      "own_goal": 0,
      "team_player_id": 1145,
      "team_id": 262,
      "id": 6462,
      "first_name": "Luka",
      "last_name": "Modrić",
      "short_name": "L. Modrić",
      "birthday": "1985-09-09",
      "trackable_object": 6472,
      "gender": "male"
    },
    {
      "player_role": {
        "id": 15,
        "position_group": "Center Forward",
        "name": "Center Forward",
        "acronym": "CF"
      },
      "start_time": "00:00:00",
      "end_time": "01:20:47",
      "number": 22,
      "yellow_card": 1,
      "red_card": 0,
      "injured": false,
      "goal": 1,
      "own_goal": 0,
      "team_player_id": 9385,
      "team_id": 284,
      "id": 12252,
      "first_name": "Raúl",
      "last_name": "de Tomás Gómez",
      "short_name": "Raúl de Tomás",
      "birthday": "1994-10-17",
      "trackable_object": 12396,
      "gender": "male"
    },
    {
      "player_role": {
        "id": 16,
        "position_group": "Wide Attacker",
        "name": "Right Forward",
        "acronym": "RF"
      },
      "start_time": "01:20:47",
      "end_time": null,
      "number": 34,
      "yellow_card": 0,
      "red_card": 0,
      "injured": false,
      "goal": 0,
      "own_goal": 0,
      "team_player_id": 247581,
      "team_id": 284,
      "id": 24666,
      "first_name": "Sergio",
      "last_name": "Camello Pérez",
      "short_name": "Sergio Camello",
      "birthday": "2001-02-10",
      "trackable_object": 25703,
      "gender": "male"
    },
    {
      "player_role": {
        "id": 15,
        "position_group": "Center Forward",
        "name": "Center Forward",
        "acronym": "CF"
      },
      "start_time": "01:20:47",
      "end_time": null,
      "number": 9,
      "yellow_card": 0,
      "red_card": 0,
      "injured": false,
      "goal": 0,
      "own_goal": 0,
      "team_player_id": 101657,
      "team_id": 284,
      "id": 8771,
      "first_name": "Radamel Falcao",
      "last_name": "García Zárate",
      "short_name": "R. Falcao",
      "birthday": "1986-02-10",
      "trackable_object": 8781,
      "gender": "male"
    },
    {
      "player_role": {
        "id": 11,
        "position_group": "Midfield",
        "name": "Attacking Midfield",
        "acronym": "AM"
      },
      "start_time": "00:00:00",
      "end_time": "01:03:23",
      "number": 8,
      "yellow_card": 0,
      "red_card": 0,
      "injured": false,
      "goal": 0,
      "own_goal": 0,
      "team_player_id": 9384,
      "team_id": 284,
      "id": 8268,
      "first_name": "Óscar Guido",
      "last_name": "Trejo",
      "short_name": "Ó. Trejo",
      "birthday": "1988-04-26",
      "trackable_object": 8278,
      "gender": "male"
    },
    {
      "player_role": {
        "id": 17,
        "position_group": "Other",
        "name": "Substitute",
        "acronym": "SUB"
      },
      "start_time": null,
      "end_time": null,
      "number": 25,
      "yellow_card": 0,
      "red_card": 0,
      "injured": false,
      "goal": 0,
      "own_goal": 0,
      "team_player_id": 1090552,
      "team_id": 262,
      "id": 11691,
      "first_name": "Kepa",
      "last_name": "Arrizabalaga Revuelta",
      "short_name": "Kepa Arrizabalaga",
      "birthday": "1994-10-03",
      "trackable_object": 11789,
      "gender": "male"
    },
    {
      "player_role": {
        "id": 17,
        "position_group": "Other",
        "name": "Substitute",
        "acronym": "SUB"
      },
      "start_time": null,
      "end_time": null,
      "number": 41,
      "yellow_card": 0,
      "red_card": 0,
      "injured": false,
      "goal": 0,
      "own_goal": 0,
      "team_player_id": 1235304,
      "team_id": 262,
      "id": 747384,
      "first_name": "Jacobo",
      "last_name": "Ramón Naveros",
      "short_name": "Jacobo Ramón",
      "birthday": "2005-01-06",
      "trackable_object": 748947,
      "gender": "male"
    },
    {
      "player_role": {
        "id": 17,
        "position_group": "Other",
        "name": "Substitute",
        "acronym": "SUB"
      },
      "start_time": null,
      "end_time": null,
      "number": 26,
      "yellow_card": 0,
      "red_card": 0,
      "injured": false,
      "goal": 0,
      "own_goal": 0,
      "team_player_id": 130007,
      "team_id": 262,
      "id": 70536,
      "first_name": "Diego",
      "last_name": "Piñeiro del Álamo",
      "short_name": "Diego Piñeiro",
      "birthday": "2004-02-13",
      "trackable_object": 71662,
      "gender": "male"
    },
    {
      "player_role": {
        "id": 17,
        "position_group": "Other",
        "name": "Substitute",
        "acronym": "SUB"
      },
      "start_time": null,
      "end_time": null,
      "number": 19,
      "yellow_card": 0,
      "red_card": 0,
      "injured": false,
      "goal": 0,
      "own_goal": 0,
      "team_player_id": 5188,
      "team_id": 262,
      "id": 2190,
      "first_name": "Daniel",
      "last_name": "Ceballos Fernández",
      "short_name": "Dani Ceballos",
      "birthday": "1996-08-07",
      "trackable_object": 2200,
      "gender": "male"
    },
    {
      "player_role": {
        "id": 0,
        "position_group": "Other",
        "name": "Goalkeeper",
        "acronym": "GK"
      },
      "start_time": "00:00:00",
      "end_time": null,
      "number": 13,
      "yellow_card": 0,
      "red_card": 0,
      "injured": false,
      "goal": 0,
      "own_goal": 0,
      "team_player_id": 6668,
      "team_id": 262,
      "id": 12248,
      "first_name": "Andriy",
      "last_name": "Lunin",
      "short_name": "A. Lunin",
      "birthday": "1999-02-11",
      "trackable_object": 12392,
      "gender": "male"
    },
    {
      "player_role": {
        "id": 17,
        "position_group": "Other",
        "name": "Substitute",
        "acronym": "SUB"
      },
      "start_time": null,
      "end_time": null,
      "number": 21,
      "yellow_card": 0,
      "red_card": 0,
      "injured": false,
      "goal": 0,
      "own_goal": 0,
      "team_player_id": 92190,
      "team_id": 284,
      "id": 25573,
      "first_name": "Pathé Ismaël",
      "last_name": "Ciss",
      "short_name": "P. Ciss",
      "birthday": "1994-03-16",
      "trackable_object": 26619,
      "gender": "male"
    },
    {
      "player_role": {
        "id": 17,
        "position_group": "Other",
        "name": "Substitute",
        "acronym": "SUB"
      },
      "start_time": null,
      "end_time": null,
      "number": 4,
      "yellow_card": 0,
      "red_card": 0,
      "injured": false,
      "goal": 0,
      "own_goal": 0,
      "team_player_id": 25579,
      "team_id": 284,
      "id": 25877,
      "first_name": "Martín",
      "last_name": "Pascual Castillo",
      "short_name": "Martín Pascual",
      "birthday": "1999-08-04",
      "trackable_object": 26938,
      "gender": "male"
    },
    {
      "player_role": {
        "id": 17,
        "position_group": "Other",
        "name": "Substitute",
        "acronym": "SUB"
      },
      "start_time": null,
      "end_time": null,
      "number": 6,
      "yellow_card": 0,
      "red_card": 0,
      "injured": false,
      "goal": 0,
      "own_goal": 0,
      "team_player_id": 9396,
      "team_id": 284,
      "id": 8735,
      "first_name": "José Ángel",
      "last_name": "Pozo la Rosa",
      "short_name": "José Pozo",
      "birthday": "1996-03-15",
      "trackable_object": 8745,
      "gender": "male"
    },
    {
      "player_role": {
        "id": 17,
        "position_group": "Other",
        "name": "Substitute",
        "acronym": "SUB"
      },
      "start_time": null,
      "end_time": null,
      "number": 13,
      "yellow_card": 0,
      "red_card": 0,
      "injured": false,
      "goal": 0,
      "own_goal": 0,
      "team_player_id": 1095500,
      "team_id": 284,
      "id": 24251,
      "first_name": "Daniel",
      "last_name": "Cárdenas Lindez",
      "short_name": "Dani Cárdenas",
      "birthday": "1997-03-28",
      "trackable_object": 25256,
      "gender": "male"
    },
    {
      "player_role": {
        "id": 17,
        "position_group": "Other",
        "name": "Substitute",
        "acronym": "SUB"
      },
      "start_time": null,
      "end_time": null,
      "number": 10,
      "yellow_card": 0,
      "red_card": 0,
      "injured": false,
      "goal": 0,
      "own_goal": 0,
      "team_player_id": 1612,
      "team_id": 284,
      "id": 1235,
      "first_name": "Tiago Manuel",
      "last_name": "Dias Correia",
      "short_name": "Bebé",
      "birthday": "1990-07-12",
      "trackable_object": 1245,
      "gender": "male"
    },
    {
      "player_role": {
        "id": 17,
        "position_group": "Other",
        "name": "Substitute",
        "acronym": "SUB"
      },
      "start_time": null,
      "end_time": null,
      "number": 2,
      "yellow_card": 0,
      "red_card": 0,
      "injured": false,
      "goal": 0,
      "own_goal": 0,
      "team_player_id": 1114343,
      "team_id": 284,
      "id": 22242,
      "first_name": "Andrei",
      "last_name": "Rațiu",
      "short_name": "A. Rațiu",
      "birthday": "1998-06-20",
      "trackable_object": 22513,
      "gender": "male"
    },
    {
      "player_role": {
        "id": 17,
        "position_group": "Other",
        "name": "Substitute",
        "acronym": "SUB"
      },
      "start_time": null,
      "end_time": null,
      "number": 16,
      "yellow_card": 0,
      "red_card": 0,
      "injured": false,
      "goal": 0,
      "own_goal": 0,
      "team_player_id": 340017,
      "team_id": 284,
      "id": 16478,
      "first_name": "Abdul",
      "last_name": "Mumin",
      "short_name": "A. Mumin",
      "birthday": "1998-06-06",
      "trackable_object": 16675,
      "gender": "male"
    },
    {
      "player_role": {
        "id": 0,
        "position_group": "Other",
        "name": "Goalkeeper",
        "acronym": "GK"
      },
      "start_time": "00:00:00",
      "end_time": null,
      "number": 1,
      "yellow_card": 0,
      "red_card": 0,
      "injured": false,
      "goal": 0,
      "own_goal": 0,
      "team_player_id": 9388,
      "team_id": 284,
      "id": 10145,
      "first_name": "Stole",
      "last_name": "Dimitrievski",
      "short_name": "S. Dimitrievski",
      "birthday": "1993-12-25",
      "trackable_object": 10155,
      "gender": "male"
    }
  ],
  "status": "closed",
  "home_team_side": [
    "right_to_left",
    "left_to_right"
  ],
  "ball": {
    "trackable_object": 55
  },
  "pitch_length": 101,
  "pitch_width": 67
}