{
  "id": 1800127,
  "home_team_score": 1,
  "away_team_score": 2,
  "date_time": "2024-10-19T19:00:00Z",
  "stadium": {
    "id": 230,
    "name": "Municipal de Balaidos",
    "city": "Vigo",
    "capacity": 31800
  },
  "home_team": {
    "id": 285,
    "name": "RC Celta de Vigo",
    "short_name": "Celta Vigo",
    "acronym": "CEL"
  },
  "home_team_kit": {
    "id": 5455,
    "team_id": 285,
    "season": {
      "id": 8,
      "start_year": 2021,
      "end_year": 2022,
      "name": "2021/2022"
    },
    "name": "Home",
    "jersey_color": "#91dbff",
    "number_color": "#000000"
  },
  "away_team": {
    "id": 262,
    "name": "Real Madrid CF",
    "short_name": "Real Madrid",
    "acronym": "REA"
  },
  "away_team_kit": {
    "id": 13860,
    "team_id": 262,
    "season": {
      "id": 95,
      "start_year": 2024,
      "end_year": 2025,
      "name": "2024/2025"
    },
    "name": "Away",
    "jersey_color": "#575757",
    "number_color": "#ffffff"
  },
  "home_team_coach": {
    "id": 963,
    "first_name": "Eduardo",
    "last_name": "Coudet"
  },
  "away_team_coach": {
    "id": 705,
    "first_name": "",
    "last_name": "Zinedine Zidane"
  },
  "competition_edition": {
    "id": 900,
    "competition": {
      "id": 4,
      "area": "ESP",
      "name": "LaLiga",
      "gender": "male",
      "age_group": "adult"
    },
    "season": {
      "id": 95,
      "start_year": 2024,
      "end_year": 2025,
      "name": "2024/2025"
    },
    "name": "ESP - LaLiga - 2024/2025"
  },
  "competition_round": {
    "id": 92,
    "name": "Round 10",
    "round_number": 10,
    "potential_overtime": false
  },
  "referees": [],
  "players": [
    {
      "player_role": {
        "id": 5,
        "position_group": "Full Back",
        "name": "Left Wing Back",
        "acronym": "LWB"
      },
      "start_time": "01:09:21",
      "end_time": null,
      "number": 23,
      "yellow_card": 0,
      "red_card": 0,
      "injured": false,
      "goal": 0,
      "own_goal": 0,
      "team_player_id": 20595,
      "team_id": 262,
      "id": 11277,
      "first_name": "Ferland",
      "last_name": "Mendy",
      "short_name": "F. Mendy",
      "birthday": "1995-06-08",
      "trackable_object": 11311,
      "gender": "male"
    },
    {
      "player_role": {
        "id": 5,
        "position_group": "Full Back",
        "name": "Left Wing Back",
        "acronym": "LWB"
      },
      "start_time": "00:00:00",
      "end_time": "01:09:21",
      "number": 20,
      "yellow_card": 0,
      "red_card": 0,
      "injured": false,
      "goal": 0,
      "own_goal": 0,
      "team_player_id": 1062965,
      "team_id": 262,
      "id": 31993,
      "first_name": "Francisco José",
      "last_name": "García Torres",
      "short_name": "Fran García",
      "birthday": "1999-08-14",
      "trackable_object": 33095,
      "gender": "male"
    },
    {
      "player_role": {
        "id": 6,
        "position_group": "Full Back",
        "name": "Right Wing Back",
        "acronym": "RWB"
      },
      "start_time": "00:00:00",
      "end_time": null,
      "number": 17,
      "yellow_card": 1,
      "red_card": 0,
      "injured": false,
      "goal": 0,
      "own_goal": 0,
      "team_player_id": 223,
      "team_id": 262,
      "id": 6373,
      "first_name": "Lucas",
      "last_name": "Vázquez Iglesias",
      "short_name": "Lucas Vázquez",
      "birthday": "1991-07-01",
      "trackable_object": 6383,
      "gender": "male"
    },
    {
      "player_role": {
        "id": 10,
        "position_group": "Midfield",
        "name": "Right Midfield",
        "acronym": "RM"
      },
      "start_time": "01:21:10",
      "end_time": null,
      "number": 19,
      "yellow_card": 0,
      "red_card": 0,
      "injured": false,
      "goal": 0,
      "own_goal": 0,
      "team_player_id": 5188,
      "team_id": 262,
      "id": 2190,
      "first_name": "Daniel",
      "last_name": "Ceballos Fernández",
      "short_name": "Dani Ceballos",
      "birthday": "1996-08-07",
      "trackable_object": 2200,
      "gender": "male"
    },
    {
      "player_role": {
        "id": 2,
        "position_group": "Central Defender",
        "name": "Center Back",
        "acronym": "CB"
      },
      "start_time": "00:00:00",
      "end_time": null,
      "number": 14,
      "yellow_card": 0,
      "red_card": 0,
      "injured": false,
      "goal": 0,
      "own_goal": 0,
      "team_player_id": 248385,
      "team_id": 262,
      "id": 12218,
      "first_name": "Aurélien",
      "last_name": "Tchouaméni",
      "short_name": "A. Tchouaméni",
      "birthday": "2000-01-27",
      "trackable_object": 12361,
      "gender": "male"
    },
    {
      "player_role": {
        "id": 10,
        "position_group": "Midfield",
        "name": "Right Midfield",
        "acronym": "RM"
      },
      "start_time": "00:00:00",
      "end_time": "01:26:05",
      "number": 8,
      "yellow_card": 0,
      "red_card": 0,
      "injured": false,
      "goal": 0,
      "own_goal": 0,
      "team_player_id": 9456,
      "team_id": 285,
      "id": 13922,
      "first_name": "Francisco José",
      "last_name": "Beltrán Peinado",
      "short_name": "Fran Beltrán",
      "birthday": "1999-02-03",
      "trackable_object": 14119,
      "gender": "male"
    },
    {
      "player_role": {
        "id": 16,
        "position_group": "Wide Attacker",
        "name": "Right Forward",
        "acronym": "RF"
      },
      "start_time": "00:00:00",
      "end_time": null,
      "number": 5,
      "yellow_card": 0,
      "red_card": 0,
      "injured": false,
      "goal": 0,
      "own_goal": 0,
      "team_player_id": 1062966,
      "team_id": 262,
      "id": 24583,
      "first_name": "Jude",
      "last_name": "Bellingham",
      "short_name": "J. Bellingham",
      "birthday": "2003-06-29",
      "trackable_object": 25615,
      "gender": "male"
    },
    {
      "player_role": {
        "id": 10,
        "position_group": "Midfield",
        "name": "Right Midfield",
        "acronym": "RM"
      },
      "start_time": "00:00:00",
      "end_time": "01:02:56",
      "number": 8,
      "yellow_card": 0,
      "red_card": 0,
      "injured": false,
      "goal": 0,
      "own_goal": 0,
      "team_player_id": 6673,
      "team_id": 262,
      "id": 12251,
      "first_name": "Federico Santiago",
      "last_name": "Valverde Dipetta",
      "short_name": "F. Valverde",
      "birthday": "1998-07-22",
      "trackable_object": 12395,
      "gender": "male"
    },
    {
      "player_role": {
        "id": 14,
        "position_group": "Wide Attacker",
        "name": "Left Forward",
        "acronym": "LF"
      },
      "start_time": "00:00:00",
      "end_time": "01:11:06",
      "number": 19,
      "yellow_card": 0,
      "red_card": 0,
      "injured": false,
      "goal": 1,
      "own_goal": 0,
      "team_player_id": 247600,
      "team_id": 285,
      "id": 61123,
      "first_name": "Williot",
      "last_name": "Swedberg",
      "short_name": "W. Swedberg",
      "birthday": "2004-02-01",
      "trackable_object": 62249,
      "gender": "male"
    },
    {
      "player_role": {
        "id": 14,
        "position_group": "Wide Attacker",
        "name": "Left Forward",
        "acronym": "LF"
      },
      "start_time": "00:00:00",
      "end_time": null,
      "number": 7,
      "yellow_card": 0,
      "red_card": 0,
      "injured": false,
      "goal": 1,
      "own_goal": 0,
      "team_player_id": 6675,
      "team_id": 262,
      "id": 12253,
      "first_name": "Vinícius José",
      "last_name": "Paixão de Oliveira Júnior",
      "short_name": "Vinícius Júnior",
      "birthday": "2000-07-12",
      "trackable_object": 12397,
      "gender": "male"
    },
    {
      "player_role": {
        "id": 4,
        "position_group": "Central Defender",
        "name": "Right Center Back",
        "acronym": "RCB"
      },
      "start_time": "00:00:00",
      "end_time": "01:11:06",
      "number": 22,
      "yellow_card": 0,
      "red_card": 0,
      "injured": false,
      "goal": 0,
      "own_goal": 0,
      "team_player_id": 1233806,
      "team_id": 285,
      "id": 4811,
      "first_name": "Javier",
      "last_name": "Manquillo Gaitán",
      "short_name": "Javi Manquillo",
      "birthday": "1994-05-05",
      "trackable_object": 4821,
      "gender": "male"
    },
    {
      "player_role": {
        "id": 2,
        "position_group": "Central Defender",
        "name": "Center Back",
        "acronym": "CB"
      },
      "start_time": "00:00:00",
      "end_time": null,
      "number": 2,
      "yellow_card": 0,
      "red_card": 0,
      "injured": false,
      "goal": 0,
      "own_goal": 0,
      "team_player_id": 1081259,
      "team_id": 285,
      "id": 27819,
      "first_name": "Carl",
      "last_name": "Starfelt",
      "short_name": "C. Starfelt",
      "birthday": "1995-06-01",
      "trackable_object": 28902,
      "gender": "male"
    },
    {
      "player_role": {
        "id": 9,
        "position_group": "Midfield",
        "name": "Left Midfield",
        "acronym": "LM"
      },
      "start_time": "01:02:56",
      "end_time": null,
      "number": 10,
      "yellow_card": 0,
      "red_card": 0,
      "injured": false,
      "goal": 0,
      "own_goal": 0,
      "team_player_id": 1145,
      "team_id": 262,
      "id": 6462,
      "first_name": "Luka",
      "last_name": "Modrić",
      "short_name": "L. Modrić",
      "birthday": "1985-09-09",
      "trackable_object": 6472,
      "gender": "male"
    },
    {
      "player_role": {
        "id": 15,
        "position_group": "Center Forward",
        "name": "Center Forward",
        "acronym": "CF"
      },
      "start_time": "00:00:00",
      "end_time": "01:21:10",
      "number": 9,
      "yellow_card": 0,
      "red_card": 0,
      "injured": false,
      "goal": 1,
      "own_goal": 0,
      "team_player_id": 59357,
      "team_id": 262,
      "id": 6028,
      "first_name": "Kylian",
      "last_name": "Mbappé Lottin",
      "short_name": "K. Mbappé",
      "birthday": "1998-12-20",
      "trackable_object": 6038,
      "gender": "male"
    },
    {
      "player_role": {
        "id": 3,
        "position_group": "Central Defender",
        "name": "Left Center Back",
        "acronym": "LCB"
      },
      "start_time": "00:00:00",
      "end_time": null,
      "number": 20,
      "yellow_card": 0,
      "red_card": 0,
      "injured": false,
      "goal": 0,
      "own_goal": 0,
      "team_player_id": 1442773,
      "team_id": 285,
      "id": 6823,
      "first_name": "Marcos ",
      "last_name": "Alonso Mendoza",
      "short_name": "Marcos Alonso",
      "birthday": "1990-12-28",
      "trackable_object": 6833,
      "gender": "male"
    },
    {
      "player_role": {
        "id": 9,
        "position_group": "Midfield",
        "name": "Left Midfield",
        "acronym": "LM"
      },
      "start_time": "00:00:00",
      "end_time": "01:02:56",
      "number": 6,
      "yellow_card": 0,
      "red_card": 0,
      "injured": false,
      "goal": 0,
      "own_goal": 0,
      "team_player_id": 100630,
      "team_id": 262,
      "id": 22103,
      "first_name": "Eduardo",
      "last_name": "Camavinga",
      "short_name": "E. Camavinga",
      "birthday": "2002-11-10",
      "trackable_object": 22340,
      "gender": "male"
    },
    {
      "player_role": {
        "id": 4,
        "position_group": "Central Defender",
        "name": "Right Center Back",
        "acronym": "RCB"
      },
      "start_time": "01:11:06",
      "end_time": null,
      "number": 32,
      "yellow_card": 0,
      "red_card": 0,
      "injured": false,
      "goal": 0,
      "own_goal": 0,
      "team_player_id": 1206314,
      "team_id": 285,
      "id": 531576,
      "first_name": "Javier",
      "last_name": "Rodríguez Galiano",
      "short_name": "Javi Rodríguez",
      "birthday": "2003-06-26",
      "trackable_object": 533133,
      "gender": "male"
    },
    {
      "player_role": {
        "id": 5,
        "position_group": "Full Back",
        "name": "Left Wing Back",
        "acronym": "LWB"
      },
      "start_time": "00:00:00",
      "end_time": null,
      "number": 30,
      "yellow_card": 0,
      "red_card": 0,
      "injured": false,
      "goal": 0,
      "own_goal": 0,
      "team_player_id": 105073,
      "team_id": 285,
      "id": 70702,
      "first_name": "Hugo",
      "last_name": "Álvarez Antúnez",
      "short_name": "Hugo Álvarez",
      "birthday": "2003-07-02",
      "trackable_object": 71828,
      "gender": "male"
    },
    {
      "player_role": {
        "id": 3,
        "position_group": "Central Defender",
        "name": "Left Center Back",
        "acronym": "LCB"
      },
      "start_time": "00:00:00",
      "end_time": null,
      "number": 22,
      "yellow_card": 0,
      "red_card": 0,
      "injured": false,
      "goal": 0,
      "own_goal": 0,
      "team_player_id": 248386,
      "team_id": 262,
      "id": 993,
      "first_name": "Antonio",
      "last_name": "Rüdiger",
      "short_name": "A. Rüdiger",
      "birthday": "1993-03-03",
      "trackable_object": 1003,
      "gender": "male"
    },
    {
      "player_role": {
        "id": 16,
        "position_group": "Wide Attacker",
        "name": "Right Forward",
        "acronym": "RF"
      },
      "start_time": "00:00:00",
      "end_time": "01:17:59",
      "number": 17,
      "yellow_card": 0,
      "red_card": 0,
      "injured": false,
      "goal": 0,
      "own_goal": 0,
      "team_player_id": 1081258,
      "team_id": 285,
      "id": 11150,
      "first_name": "Jonathan",
      "last_name": "Bamba",
      "short_name": "J. Bamba",
      "birthday": "1996-03-26",
      "trackable_object": 11162,
      "gender": "male"
    },
    {
      "player_role": {
        "id": 4,
        "position_group": "Central Defender",
        "name": "Right Center Back",
        "acronym": "RCB"
      },
      "start_time": "00:00:00",
      "end_time": null,
      "number": 3,
      "yellow_card": 0,
      "red_card": 0,
      "injured": false,
      "goal": 0,
      "own_goal": 0,
      "team_player_id": 20597,
      "team_id": 262,
      "id": 12662,
      "first_name": "Éder Gabriel",
      "last_name": "Militão",
      "short_name": "Éder Militão",
      "birthday": "1998-01-18",
      "trackable_object": 12821,
      "gender": "male"
    },
    {
      "player_role": {
        "id": 15,
        "position_group": "Center Forward",
        "name": "Center Forward",
        "acronym": "CF"
      },
      "start_time": "01:17:59",
      "end_time": null,
      "number": 9,
      "yellow_card": 0,
      "red_card": 0,
      "injured": false,
      "goal": 0,
      "own_goal": 0,
      "team_player_id": 1111949,
      "team_id": 285,
      "id": 15339,
      "first_name": "Anastasios",
      "last_name": "Douvikas",
      "short_name": "T. Douvikas",
      "birthday": "1999-08-02",
      "trackable_object": 15536,
      "gender": "male"
    },
    {
      "player_role": {
        "id": 6,
        "position_group": "Full Back",
        "name": "Right Wing Back",
        "acronym": "RWB"
      },
      "start_time": "01:02:56",
      "end_time": null,
      "number": 11,
      "yellow_card": 0,
      "red_card": 0,
      "injured": false,
      "goal": 0,
      "own_goal": 0,
      "team_player_id": 21859,
      "team_id": 262,
      "id": 23903,
      "first_name": "Rodrygo",
      "last_name": "Silva de Goes",
      "short_name": "Rodrygo",
      "birthday": "2001-01-09",
      "trackable_object": 24861,
      "gender": "male"
    },
    {
      "player_role": {
        "id": 6,
        "position_group": "Full Back",
        "name": "Right Wing Back",
        "acronym": "RWB"
      },
      "start_time": "00:00:00",
      "end_time": null,
      "number": 3,
      "yellow_card": 0,
      "red_card": 0,
      "injured": false,
      "goal": 0,
      "own_goal": 0,
      "team_player_id": 247602,
      "team_id": 285,
      "id": 29801,
      "first_name": "Óscar",
      "last_name": "Mingueza García",
      "short_name": "Óscar Mingueza",
      "birthday": "1999-05-13",
      "trackable_object": 30894,
      "gender": "male"
    },
    {
      "player_role": {
        "id": 10,
        "position_group": "Midfield",
        "name": "Right Midfield",
        "acronym": "RM"
      },
      "start_time": "01:26:05",
      "end_time": null,
      "number": 25,
      "yellow_card": 0,
      "red_card": 0,
      "injured": false,
      "goal": 0,
      "own_goal": 0,
      "team_player_id": 221006,
      "team_id": 285,
      "id": 162275,
      "first_name": "Damián",
      "last_name": "Rodríguez Sousa",
      "short_name": "Damián Rodríguez",
      "birthday": "2003-03-17",
      "trackable_object": 163830,
      "gender": "male"
    },
    {
      "player_role": {
        "id": 14,
        "position_group": "Wide Attacker",
        "name": "Left Forward",
        "acronym": "LF"
      },
      "start_time": "01:11:06",
      "end_time": null,
      "number": 12,
      "yellow_card": 1,
      "red_card": 0,
      "injured": false,
      "goal": 0,
      "own_goal": 0,
      "team_player_id": 40973,
      "team_id": 285,
      "id": 35622,
      "first_name": "Alfonso",
      "last_name": "González Martínez",
      "short_name": "Alfon González",
      "birthday": "1999-05-04",
      "trackable_object": 36743,
      "gender": "male"
    },
    {
      "player_role": {
        "id": 16,
        "position_group": "Wide Attacker",
        "name": "Right Forward",
        "acronym": "RF"
      },
      "start_time": "01:17:59",
      "end_time": null,
      "number": 18,
      "yellow_card": 0,
      "red_card": 0,
      "injured": false,
      "goal": 0,
      "own_goal": 0,
      "team_player_id": 431037,
      "team_id": 285,
      "id": 296080,
      "first_name": "Pablo",
      "last_name": "Durán Fernández",
      "short_name": "Pablo Durán",
      "birthday": "2001-05-25",
      "trackable_object": 297637,
      "gender": "male"
    },
    {
      "player_role": {
        "id": 9,
        "position_group": "Midfield",
        "name": "Left Midfield",
        "acronym": "LM"
      },
      "start_time": "00:00:00",
      "end_time": null,
      "number": 33,
      "yellow_card": 1,
      "red_card": 0,
      "injured": false,
      "goal": 0,
      "own_goal": 0,
      "team_player_id": 65616,
      "team_id": 285,
      "id": 46579,
      "first_name": "Hugo",
      "last_name": "Sotelo Gómez",
      "short_name": "Hugo Sotelo",
      "birthday": "2003-12-19",
      "trackable_object": 47705,
      "gender": "male"
    },
    {
      "player_role": {
        "id": 15,
        "position_group": "Center Forward",
        "name": "Center Forward",
        "acronym": "CF"
      },
      "start_time": "00:00:00",
      "end_time": "01:17:59",
      "number": 7,
      "yellow_card": 0,
      "red_card": 0,
      "injured": false,
      "goal": 0,
      "own_goal": 0,
      "team_player_id": 1338967,
      "team_id": 285,
      "id": 13930,
      "first_name": "Borja",
      "last_name": "Iglesias Quintas",
      "short_name": "Borja Iglesias",
      "birthday": "1993-01-17",
      "trackable_object": 14127,
      "gender": "male"
    },
    {
      "player_role": {
        "id": 17,
        "position_group": "Other",
        "name": "Substitute",
        "acronym": "SUB"
      },
      "start_time": null,
      "end_time": null,
      "number": 34,
      "yellow_card": 0,
      "red_card": 0,
      "injured": false,
      "goal": 0,
      "own_goal": 0,
      "team_player_id": 1441532,
      "team_id": 262,
      "id": 120539,
      "first_name": "Sergio",
      "last_name": "Mestre Sánchez",
      "short_name": "Sergio Mestre",
      "birthday": "2005-02-13",
      "trackable_object": 122094,
      "gender": "male"
    },
    {
      "player_role": {
        "id": 17,
        "position_group": "Other",
        "name": "Substitute",
        "acronym": "SUB"
      },
      "start_time": null,
      "end_time": null,
      "number": 18,
      "yellow_card": 0,
      "red_card": 0,
      "injured": false,
      "goal": 0,
      "own_goal": 0,
      "team_player_id": 5186,
      "team_id": 262,
      "id": 11607,
      "first_name": "Jesús",
      "last_name": "Vallejo Lázaro",
      "short_name": "Jesús Vallejo",
      "birthday": "1997-01-05",
      "trackable_object": 11695,
      "gender": "male"
    },
    {
      "player_role": {
        "id": 17,
        "position_group": "Other",
        "name": "Substitute",
        "acronym": "SUB"
      },
      "start_time": null,
      "end_time": null,
      "number": 16,
      "yellow_card": 0,
      "red_card": 0,
      "injured": false,
      "goal": 0,
      "own_goal": 0,
      "team_player_id": 1349625,
      "team_id": 262,
      "id": 259174,
      "first_name": "Endrick Felipe",
      "last_name": "Moreira de Sousa",
      "short_name": "Endrick",
      "birthday": "2006-07-21",
      "trackable_object": 260731,
      "gender": "male"
    },
    {
      "player_role": {
        "id": 17,
        "position_group": "Other",
        "name": "Substitute",
        "acronym": "SUB"
      },
      "start_time": null,
      "end_time": null,
      "number": 13,
      "yellow_card": 0,
      "red_card": 0,
      "injured": false,
      "goal": 0,
      "own_goal": 0,
      "team_player_id": 6668,
      "team_id": 262,
      "id": 12248,
      "first_name": "Andriy",
      "last_name": "Lunin",
      "short_name": "A. Lunin",
      "birthday": "1999-02-11",
      "trackable_object": 12392,
      "gender": "male"
    },
    {
      "player_role": {
        "id": 17,
        "position_group": "Other",
        "name": "Substitute",
        "acronym": "SUB"
      },
      "start_time": null,
      "end_time": null,
      "number": 15,
      "yellow_card": 0,
      "red_card": 0,
      "injured": false,
      "goal": 0,
      "own_goal": 0,
      "team_player_id": 1062967,
      "team_id": 262,
      "id": 44876,
      "first_name": "Arda",
      "last_name": "Güler",
      "short_name": "A. Güler",
      "birthday": "2005-02-25",
      "trackable_object": 46002,
      "gender": "male"
    },
    {
      "player_role": {
        "id": 0,
        "position_group": "Other",
        "name": "Goalkeeper",
        "acronym": "GK"
      },
      "start_time": "00:00:00",
      "end_time": null,
      "number": 1,
      "yellow_card": 0,
      "red_card": 0,
      "injured": false,
      "goal": 0,
      "own_goal": 0,
      "team_player_id": 6666,
      "team_id": 262,
      "id": 10261,
      "first_name": "Thibaut",
      "last_name": "Courtois",
      "short_name": "T. Courtois",
      "birthday": "1992-05-11",
      "trackable_object": 10271,
      "gender": "male"
    },
    {
      "player_role": {
        "id": 17,
        "position_group": "Other",
        "name": "Substitute",
        "acronym": "SUB"
      },
      "start_time": null,
      "end_time": null,
      "number": 23,
      "yellow_card": 0,
      "red_card": 0,
      "injured": false,
      "goal": 0,
      "own_goal": 0,
      "team_player_id": 1233807,
      "team_id": 285,
      "id": 116282,
      "first_name": "Tadeo",
      "last_name": "Allende",
      "short_name": "T. Allende",
      "birthday": "1999-02-20",
      "trackable_object": 117834,
      "gender": "male"
    },
    {
      "player_role": {
        "id": 17,
        "position_group": "Other",
        "name": "Substitute",
        "acronym": "SUB"
      },
      "start_time": null,
      "end_time": null,
      "number": 5,
      "yellow_card": 0,
      "red_card": 0,
      "injured": false,
      "goal": 0,
      "own_goal": 0,
      "team_player_id": 22895,
      "team_id": 285,
      "id": 24300,
      "first_name": "Sergio",
      "last_name": "Carreira Vilariño",
      "short_name": "Sergio Carreira",
      "birthday": "2000-10-13",
      "trackable_object": 25309,
      "gender": "male"
    },
    {
      "player_role": {
        "id": 17,
        "position_group": "Other",
        "name": "Substitute",
        "acronym": "SUB"
      },
      "start_time": null,
      "end_time": null,
      "number": 21,
      "yellow_card": 0,
      "red_card": 0,
      "injured": false,
      "goal": 0,
      "own_goal": 0,
      "team_player_id": 1131350,
      "team_id": 285,
      "id": 16710,
      "first_name": "Mihailo",
      "last_name": "Ristić",
      "short_name": "M. Ristić",
      "birthday": "1995-10-31",
      "trackable_object": 16907,
      "gender": "male"
    },
    {
      "player_role": {
        "id": 17,
        "position_group": "Other",
        "name": "Substitute",
        "acronym": "SUB"
      },
      "start_time": null,
      "end_time": null,
      "number": 16,
      "yellow_card": 0,
      "red_card": 0,
      "injured": false,
      "goal": 0,
      "own_goal": 0,
      "team_player_id": 1227225,
      "team_id": 285,
      "id": 13767,
      "first_name": "Jailson",
      "last_name": "Marques Siqueira",
      "short_name": "Jailson",
      "birthday": "1995-09-07",
      "trackable_object": 13964,
      "gender": "male"
    },
    {
      "player_role": {
        "id": 17,
        "position_group": "Other",
        "name": "Substitute",
        "acronym": "SUB"
      },
      "start_time": null,
      "end_time": null,
      "number": 1,
      "yellow_card": 0,
      "red_card": 0,
      "injured": false,
      "goal": 0,
      "own_goal": 0,
      "team_player_id": 9470,
      "team_id": 285,
      "id": 13927,
      "first_name": "Iván",
      "last_name": "Villar Martínez",
      "short_name": "Iván Villar",
      "birthday": "1997-07-09",
      "trackable_object": 14124,
      "gender": "male"
    },
    {
      "player_role": {
        "id": 17,
        "position_group": "Other",
        "name": "Substitute",
        "acronym": "SUB"
      },
      "start_time": null,
      "end_time": null,
      "number": 11,
      "yellow_card": 0,
      "red_card": 0,
      "injured": false,
      "goal": 0,
      "own_goal": 0,
      "team_player_id": 92081,
      "team_id": 285,
      "id": 11568,
      "first_name": "Franco Emanuel",
      "last_name": "Cervi",
      "short_name": "F. Cervi",
      "birthday": "1994-05-26",
      "trackable_object": 11647,
      "gender": "male"
    },
    {
      "player_role": {
        "id": 17,
        "position_group": "Other",
        "name": "Substitute",
        "acronym": "SUB"
      },
      "start_time": null,
      "end_time": null,
      "number": 24,
      "yellow_card": 0,
      "red_card": 0,
      "injured": false,
      "goal": 0,
      "own_goal": 0,
      "team_player_id": 171832,
      "team_id": 285,
      "id": 126372,
      "first_name": "Carlos",
      "last_name": "Domínguez Cáceres",
      "short_name": "Carlos Domínguez",
      "birthday": "2001-02-11",
      "trackable_object": 127927,
      "gender": "male"
    },
    {
      "player_role": {
        "id": 0,
        "position_group": "Other",
        "name": "Goalkeeper",
        "acronym": "GK"
      },
      "start_time": "00:00:00",
      "end_time": null,
      "number": 13,
      "yellow_card": 0,
      "red_card": 0,
      "injured": false,
      "goal": 0,
      "own_goal": 0,
      "team_player_id": 1131351,
      "team_id": 285,
      "id": 10662,
      "first_name": "Vicente",
      "last_name": "Guaita Panadero",
      "short_name": "Vicente Guaita",
      "birthday": "1987-01-10",
      "trackable_object": 10672,
      "gender": "male"
    }
  ],
  "status": "closed",
  "home_team_side": [
    "left_to_right",
    "right_to_left"
  ],
  "ball": {
    "trackable_object": 55
  },
  "pitch_length": 105,
  "pitch_width": 68
}