{
  "id": 1992355,
  "home_team_score": 0,
  "away_team_score": 3,
  "date_time": "2025-01-29T20:00:00Z",
  "stadium": {
    "id": 123,
    "name": "Stade de Roudourou",
    "city": "Guingamp",
    "capacity": 18378
  },
  "home_team": {
    "id": 89,
    "name": "Stade Brestois 29",
    "short_name": "Stade Brestois",
    "acronym": "BRE"
  },
  "home_team_kit": {
    "id": 10984,
    "team_id": 89,
    "season": {
      "id": 29,
      "start_year": 2024,
      "end_year": 2024,
      "name": "2024"
    },
    "name": "Away",
    "jersey_color": "#f20202",
    "number_color": "#ffffff"
  },
  "away_team": {
    "id": 262,
    "name": "Real Madrid CF",
    "short_name": "Real Madrid",
    "acronym": "REA"
  },
  "away_team_kit": {
    "id": 20,
    "team_id": 262,
    "season": {
      "id": 3,
      "start_year": 2016,
      "end_year": 2017,
      "name": "2016/2017"
    },
    "name": "home",
    "jersey_color": "#ffffff",
    "number_color": "#000000"
  },
  "home_team_coach": {
    "id": 115,
    "first_name": "Olivier",
    "last_name": "Dall'Oglio"
  },
  "away_team_coach": {
    "id": 705,
    "first_name": "",
    "last_name": "Zinedine Zidane"
  },
  "competition_edition": {
    "id": 948,
    "competition": {
      "id": 10,
      "area": "UEFA",
      "name": "Champions League",
      "gender": "male",
      "age_group": "adult"
    },
    "season": {
      "id": 95,
      "start_year": 2024,
      "end_year": 2025,
      "name": "2024/2025"
    },
    "name": "UEFA - Champions League - 2024/2025"
  },
  "competition_round": {
    "id": 249,
    "name": "Play-Offs - 2nd Leg",
    "round_number": 8,
    "potential_overtime": true
  },
  "referees": [],
  "players": [
    {
      "player_role": {
        "id": 12,
        "position_group": "Wide Attacker",
        "name": "Left Winger",
        "acronym": "LW"
      },
      "start_time": "01:19:03",
      "end_time": null,
      "number": 34,
      "yellow_card": 0,
      "red_card": 0,
      "injured": false,
      "goal": 0,
      "own_goal": 0,
      "team_player_id": 1441582,
      "team_id": 89,
      "id": 174563,
      "first_name": "Ibrahim",
      "last_name": "Salah",
      "short_name": "I. Salah",
      "birthday": "2001-08-30",
      "trackable_object": 176118,
      "gender": "male"
    },
    {
      "player_role": {
        "id": 15,
        "position_group": "Center Forward",
        "name": "Center Forward",
        "acronym": "CF"
      },
      "start_time": "00:00:00",
      "end_time": "01:09:24",
      "number": 14,
      "yellow_card": 0,
      "red_card": 0,
      "injured": false,
      "goal": 0,
      "own_goal": 0,
      "team_player_id": 1441583,
      "team_id": 89,
      "id": 16108,
      "first_name": "Mama Samba",
      "last_name": "Baldé",
      "short_name": "Mama Baldé",
      "birthday": "1995-11-06",
      "trackable_object": 16305,
      "gender": "male"
    },
    {
      "player_role": {
        "id": 11,
        "position_group": "Midfield",
        "name": "Attacking Midfield",
        "acronym": "AM"
      },
      "start_time": "00:00:00",
      "end_time": "01:00:26",
      "number": 9,
      "yellow_card": 0,
      "red_card": 0,
      "injured": false,
      "goal": 0,
      "own_goal": 0,
      "team_player_id": 1141300,
      "team_id": 89,
      "id": 81372,
      "first_name": "Kamory",
      "last_name": "Doumbia",
      "short_name": "K. Doumbia",
      "birthday": "2003-02-18",
      "trackable_object": 82505,
      "gender": "male"
    },
    {
      "player_role": {
        "id": 21,
        "position_group": "Midfield",
        "name": "Left Defensive Midfield",
        "acronym": "LDM"
      },
      "start_time": "01:22:14",
      "end_time": null,
      "number": 19,
      "yellow_card": 0,
      "red_card": 0,
      "injured": false,
      "goal": 0,
      "own_goal": 0,
      "team_player_id": 5188,
      "team_id": 262,
      "id": 2190,
      "first_name": "Daniel",
      "last_name": "Ceballos Fernández",
      "short_name": "Dani Ceballos",
      "birthday": "1996-08-07",
      "trackable_object": 2200,
      "gender": "male"
    },
    {
      "player_role": {
        "id": 10,
        "position_group": "Midfield",
        "name": "Right Midfield",
        "acronym": "RM"
      },
      "start_time": "00:00:00",
      "end_time": "01:09:24",
      "number": 45,
      "yellow_card": 0,
      "red_card": 0,
      "injured": false,
      "goal": 0,
      "own_goal": 0,
      "team_player_id": 59079,
      "team_id": 89,
      "id": 12285,
      "first_name": "Mahdi",
      "last_name": "Camara",
      "short_name": "M. Camara",
      "birthday": "1998-06-30",
      "trackable_object": 12429,
      "gender": "male"
    },
    {
      "player_role": {
        "id": 9,
        "position_group": "Midfield",
        "name": "Left Midfield",
        "acronym": "LM"
      },
      "start_time": "00:00:00",
      "end_time": "01:22:14",
      "number": 5,
      "yellow_card": 1,
      "red_card": 0,
      "injured": false,
      "goal": 1,
      "own_goal": 0,
      "team_player_id": 1062966,
      "team_id": 262,
      "id": 24583,
      "first_name": "Jude",
      "last_name": "Bellingham",
      "short_name": "J. Bellingham",
      "birthday": "2003-06-29",
      "trackable_object": 25615,
      "gender": "male"
    },
    {
      "player_role": {
        "id": 10,
        "position_group": "Midfield",
        "name": "Right Midfield",
        "acronym": "RM"
      },
      "start_time": "00:00:00",
      "end_time": "01:27:08",
      "number": 10,
      "yellow_card": 0,
      "red_card": 0,
      "injured": false,
      "goal": 0,
      "own_goal": 0,
      "team_player_id": 1145,
      "team_id": 262,
      "id": 6462,
      "first_name": "Luka",
      "last_name": "Modrić",
      "short_name": "L. Modrić",
      "birthday": "1985-09-09",
      "trackable_object": 6472,
      "gender": "male"
    },
    {
      "player_role": {
        "id": 3,
        "position_group": "Central Defender",
        "name": "Left Center Back",
        "acronym": "LCB"
      },
      "start_time": "01:22:14",
      "end_time": null,
      "number": 4,
      "yellow_card": 0,
      "red_card": 0,
      "injured": false,
      "goal": 0,
      "own_goal": 0,
      "team_player_id": 91761,
      "team_id": 262,
      "id": 2395,
      "first_name": "David",
      "last_name": "Olatukunbo Alaba",
      "short_name": "D. Alaba",
      "birthday": "1992-06-24",
      "trackable_object": 2405,
      "gender": "male"
    },
    {
      "player_role": {
        "id": 4,
        "position_group": "Central Defender",
        "name": "Right Center Back",
        "acronym": "RCB"
      },
      "start_time": "00:00:00",
      "end_time": "01:22:14",
      "number": 14,
      "yellow_card": 1,
      "red_card": 0,
      "injured": false,
      "goal": 0,
      "own_goal": 0,
      "team_player_id": 248385,
      "team_id": 262,
      "id": 12218,
      "first_name": "Aurélien",
      "last_name": "Tchouaméni",
      "short_name": "A. Tchouaméni",
      "birthday": "2000-01-27",
      "trackable_object": 12361,
      "gender": "male"
    },
    {
      "player_role": {
        "id": 13,
        "position_group": "Wide Attacker",
        "name": "Right Winger",
        "acronym": "RW"
      },
      "start_time": "01:11:48",
      "end_time": null,
      "number": 15,
      "yellow_card": 0,
      "red_card": 0,
      "injured": false,
      "goal": 0,
      "own_goal": 0,
      "team_player_id": 1062967,
      "team_id": 262,
      "id": 44876,
      "first_name": "Arda",
      "last_name": "Güler",
      "short_name": "A. Güler",
      "birthday": "2005-02-25",
      "trackable_object": 46002,
      "gender": "male"
    },
    {
      "player_role": {
        "id": 15,
        "position_group": "Center Forward",
        "name": "Center Forward",
        "acronym": "CF"
      },
      "start_time": "00:00:00",
      "end_time": "01:19:03",
      "number": 19,
      "yellow_card": 0,
      "red_card": 0,
      "injured": false,
      "goal": 0,
      "own_goal": 0,
      "team_player_id": 1342457,
      "team_id": 89,
      "id": 12230,
      "first_name": "Ludovic",
      "last_name": "Ajorque",
      "short_name": "L. Ajorque",
      "birthday": "1994-02-25",
      "trackable_object": 12373,
      "gender": "male"
    },
    {
      "player_role": {
        "id": 13,
        "position_group": "Wide Attacker",
        "name": "Right Winger",
        "acronym": "RW"
      },
      "start_time": "01:09:24",
      "end_time": null,
      "number": 10,
      "yellow_card": 0,
      "red_card": 0,
      "injured": false,
      "goal": 0,
      "own_goal": 0,
      "team_player_id": 101899,
      "team_id": 89,
      "id": 12465,
      "first_name": "Romain",
      "last_name": "Del Castillo",
      "short_name": "R. Del Castillo",
      "birthday": "1996-03-29",
      "trackable_object": 12614,
      "gender": "male"
    },
    {
      "player_role": {
        "id": 13,
        "position_group": "Wide Attacker",
        "name": "Right Winger",
        "acronym": "RW"
      },
      "start_time": "00:00:00",
      "end_time": "01:11:48",
      "number": 21,
      "yellow_card": 0,
      "red_card": 0,
      "injured": false,
      "goal": 0,
      "own_goal": 0,
      "team_player_id": 18355,
      "team_id": 262,
      "id": 11592,
      "first_name": "Brahim",
      "last_name": "Abdelkader Diaz",
      "short_name": "Brahim Diaz",
      "birthday": "1999-08-03",
      "trackable_object": 11673,
      "gender": "male"
    },
    {
      "player_role": {
        "id": 13,
        "position_group": "Wide Attacker",
        "name": "Right Winger",
        "acronym": "RW"
      },
      "start_time": "01:27:08",
      "end_time": null,
      "number": 16,
      "yellow_card": 0,
      "red_card": 0,
      "injured": false,
      "goal": 0,
      "own_goal": 0,
      "team_player_id": 1349625,
      "team_id": 262,
      "id": 259174,
      "first_name": "Endrick Felipe",
      "last_name": "Moreira de Sousa",
      "short_name": "Endrick",
      "birthday": "2006-07-21",
      "trackable_object": 260731,
      "gender": "male"
    },
    {
      "player_role": {
        "id": 20,
        "position_group": "Full Back",
        "name": "Right Back",
        "acronym": "RB"
      },
      "start_time": "00:00:00",
      "end_time": "01:22:14",
      "number": 17,
      "yellow_card": 0,
      "red_card": 0,
      "injured": false,
      "goal": 0,
      "own_goal": 0,
      "team_player_id": 223,
      "team_id": 262,
      "id": 6373,
      "first_name": "Lucas",
      "last_name": "Vázquez Iglesias",
      "short_name": "Lucas Vázquez",
      "birthday": "1991-07-01",
      "trackable_object": 6383,
      "gender": "male"
    },
    {
      "player_role": {
        "id": 20,
        "position_group": "Full Back",
        "name": "Right Back",
        "acronym": "RB"
      },
      "start_time": "01:22:14",
      "end_time": null,
      "number": 35,
      "yellow_card": 0,
      "red_card": 0,
      "injured": false,
      "goal": 0,
      "own_goal": 0,
      "team_player_id": 1511475,
      "team_id": 262,
      "id": 70532,
      "first_name": "Raúl",
      "last_name": "Asencio del Rosario",
      "short_name": "Raúl Asencio",
      "birthday": "2003-02-13",
      "trackable_object": 71658,
      "gender": "male"
    },
    {
      "player_role": {
        "id": 12,
        "position_group": "Wide Attacker",
        "name": "Left Winger",
        "acronym": "LW"
      },
      "start_time": "01:09:24",
      "end_time": null,
      "number": 17,
      "yellow_card": 0,
      "red_card": 0,
      "injured": false,
      "goal": 0,
      "own_goal": 0,
      "team_player_id": 1387748,
      "team_id": 89,
      "id": 34074,
      "first_name": "Abdallah Dipo",
      "last_name": "Sima",
      "short_name": "A. Sima",
      "birthday": "2001-06-17",
      "trackable_object": 35183,
      "gender": "male"
    },
    {
      "player_role": {
        "id": 11,
        "position_group": "Midfield",
        "name": "Attacking Midfield",
        "acronym": "AM"
      },
      "start_time": "01:00:26",
      "end_time": null,
      "number": 21,
      "yellow_card": 0,
      "red_card": 0,
      "injured": false,
      "goal": 0,
      "own_goal": 0,
      "team_player_id": 31781,
      "team_id": 89,
      "id": 13419,
      "first_name": "Romain",
      "last_name": "Faivre",
      "short_name": "R. Faivre",
      "birthday": "1998-07-14",
      "trackable_object": 13616,
      "gender": "male"
    },
    {
      "player_role": {
        "id": 9,
        "position_group": "Midfield",
        "name": "Left Midfield",
        "acronym": "LM"
      },
      "start_time": "00:00:00",
      "end_time": "01:00:26",
      "number": 8,
      "yellow_card": 0,
      "red_card": 0,
      "injured": false,
      "goal": 0,
      "own_goal": 0,
      "team_player_id": 15545,
      "team_id": 89,
      "id": 18404,
      "first_name": "Hugo",
      "last_name": "Magnetti",
      "short_name": "H. Magnetti",
      "birthday": "1998-05-30",
      "trackable_object": 18601,
      "gender": "male"
    },
    {
      "player_role": {
        "id": 21,
        "position_group": "Midfield",
        "name": "Left Defensive Midfield",
        "acronym": "LDM"
      },
      "start_time": "01:00:26",
      "end_time": null,
      "number": 20,
      "yellow_card": 0,
      "red_card": 0,
      "injured": false,
      "goal": 0,
      "own_goal": 0,
      "team_player_id": 240885,
      "team_id": 89,
      "id": 11163,
      "first_name": "Pierre",
      "last_name": "Lees-Melou",
      "short_name": "P. Lees-Melou",
      "birthday": "1993-05-25",
      "trackable_object": 11181,
      "gender": "male"
    },
    {
      "player_role": {
        "id": 17,
        "position_group": "Other",
        "name": "Substitute",
        "acronym": "SUB"
      },
      "start_time": null,
      "end_time": null,
      "number": 34,
      "yellow_card": 0,
      "red_card": 0,
      "injured": false,
      "goal": 0,
      "own_goal": 0,
      "team_player_id": 1441532,
      "team_id": 262,
      "id": 120539,
      "first_name": "Sergio",
      "last_name": "Mestre Sánchez",
      "short_name": "Sergio Mestre",
      "birthday": "2005-02-13",
      "trackable_object": 122094,
      "gender": "male"
    },
    {
      "player_role": {
        "id": 17,
        "position_group": "Other",
        "name": "Substitute",
        "acronym": "SUB"
      },
      "start_time": null,
      "end_time": null,
      "number": 47,
      "yellow_card": 0,
      "red_card": 0,
      "injured": false,
      "goal": 0,
      "own_goal": 0,
      "team_player_id": 1555177,
      "team_id": 262,
      "id": 120531,
      "first_name": "Pol",
      "last_name": "Fortuny Aubareda",
      "short_name": "Pol Fortuny",
      "birthday": "2005-03-11",
      "trackable_object": 122086,
      "gender": "male"
    },
    {
      "player_role": {
        "id": 17,
        "position_group": "Other",
        "name": "Substitute",
        "acronym": "SUB"
      },
      "start_time": null,
      "end_time": null,
      "number": 31,
      "yellow_card": 0,
      "red_card": 0,
      "injured": false,
      "goal": 0,
      "own_goal": 0,
      "team_player_id": 1235304,
      "team_id": 262,
      "id": 747384,
      "first_name": "Jacobo",
      "last_name": "Ramón Naveros",
      "short_name": "Jacobo Ramón",
      "birthday": "2005-01-06",
      "trackable_object": 748947,
      "gender": "male"
    },
    {
      "player_role": {
        "id": 17,
        "position_group": "Other",
        "name": "Substitute",
        "acronym": "SUB"
      },
      "start_time": null,
      "end_time": null,
      "number": 30,
      "yellow_card": 0,
      "red_card": 0,
      "injured": false,
      "goal": 0,
      "own_goal": 0,
      "team_player_id": 1113705,
      "team_id": 262,
      "id": 70520,
      "first_name": "Gonzalo",
      "last_name": "García Torres",
      "short_name": "Gonzalo García",
      "birthday": "2004-03-24",
      "trackable_object": 71646,
      "gender": "male"
    },
    {
      "player_role": {
        "id": 17,
        "position_group": "Other",
        "name": "Substitute",
        "acronym": "SUB"
      },
      "start_time": null,
      "end_time": null,
      "number": 20,
      "yellow_card": 0,
      "red_card": 0,
      "injured": false,
      "goal": 0,
      "own_goal": 0,
      "team_player_id": 1062965,
      "team_id": 262,
      "id": 31993,
      "first_name": "Francisco José",
      "last_name": "García Torres",
      "short_name": "Fran García",
      "birthday": "1999-08-14",
      "trackable_object": 33095,
      "gender": "male"
    },
    {
      "player_role": {
        "id": 17,
        "position_group": "Other",
        "name": "Substitute",
        "acronym": "SUB"
      },
      "start_time": null,
      "end_time": null,
      "number": 13,
      "yellow_card": 0,
      "red_card": 0,
      "injured": false,
      "goal": 0,
      "own_goal": 0,
      "team_player_id": 6668,
      "team_id": 262,
      "id": 12248,
      "first_name": "Andriy",
      "last_name": "Lunin",
      "short_name": "A. Lunin",
      "birthday": "1999-02-11",
      "trackable_object": 12392,
      "gender": "male"
    },
    {
      "player_role": {
        "id": 0,
        "position_group": "Other",
        "name": "Goalkeeper",
        "acronym": "GK"
      },
      "start_time": "00:00:00",
      "end_time": null,
      "number": 1,
      "yellow_card": 0,
      "red_card": 0,
      "injured": false,
      "goal": 0,
      "own_goal": 0,
      "team_player_id": 6666,
      "team_id": 262,
      "id": 10261,
      "first_name": "Thibaut",
      "last_name": "Courtois",
      "short_name": "T. Courtois",
      "birthday": "1992-05-11",
      "trackable_object": 10271,
      "gender": "male"
    },
    {
      "player_role": {
        "id": 12,
        "position_group": "Wide Attacker",
        "name": "Left Winger",
        "acronym": "LW"
      },
      "start_time": "00:00:00",
      "end_time": null,
      "number": 11,
      "yellow_card": 0,
      "red_card": 0,
      "injured": false,
      "goal": 2,
      "own_goal": 0,
      "team_player_id": 21859,
      "team_id": 262,
      "id": 23903,
      "first_name": "Rodrygo",
      "last_name": "Silva de Goes",
      "short_name": "Rodrygo",
      "birthday": "2001-01-09",
      "trackable_object": 24861,
      "gender": "male"
    },
    {
      "player_role": {
        "id": 15,
        "position_group": "Center Forward",
        "name": "Center Forward",
        "acronym": "CF"
      },
      "start_time": "00:00:00",
      "end_time": null,
      "number": 9,
      "yellow_card": 0,
      "red_card": 0,
      "injured": false,
      "goal": 0,
      "own_goal": 0,
      "team_player_id": 59357,
      "team_id": 262,
      "id": 6028,
      "first_name": "Kylian",
      "last_name": "Mbappé Lottin",
      "short_name": "K. Mbappé",
      "birthday": "1998-12-20",
      "trackable_object": 6038,
      "gender": "male"
    },
    {
      "player_role": {
        "id": 7,
        "position_group": "Midfield",
        "name": "Defensive Midfield",
        "acronym": "DM"
      },
      "start_time": "00:00:00",
      "end_time": null,
      "number": 8,
      "yellow_card": 0,
      "red_card": 0,
      "injured": false,
      "goal": 0,
      "own_goal": 0,
      "team_player_id": 6673,
      "team_id": 262,
      "id": 12251,
      "first_name": "Federico Santiago",
      "last_name": "Valverde Dipetta",
      "short_name": "F. Valverde",
      "birthday": "1998-07-22",
      "trackable_object": 12395,
      "gender": "male"
    },
    {
      "player_role": {
        "id": 19,
        "position_group": "Full Back",
        "name": "Left Back",
        "acronym": "LB"
      },
      "start_time": "00:00:00",
      "end_time": null,
      "number": 23,
      "yellow_card": 0,
      "red_card": 0,
      "injured": false,
      "goal": 0,
      "own_goal": 0,
      "team_player_id": 20595,
      "team_id": 262,
      "id": 11277,
      "first_name": "Ferland",
      "last_name": "Mendy",
      "short_name": "F. Mendy",
      "birthday": "1995-06-08",
      "trackable_object": 11311,
      "gender": "male"
    },
    {
      "player_role": {
        "id": 3,
        "position_group": "Central Defender",
        "name": "Left Center Back",
        "acronym": "LCB"
      },
      "start_time": "00:00:00",
      "end_time": null,
      "number": 22,
      "yellow_card": 1,
      "red_card": 0,
      "injured": false,
      "goal": 0,
      "own_goal": 0,
      "team_player_id": 248386,
      "team_id": 262,
      "id": 993,
      "first_name": "Antonio",
      "last_name": "Rüdiger",
      "short_name": "A. Rüdiger",
      "birthday": "1993-03-03",
      "trackable_object": 1003,
      "gender": "male"
    },
    {
      "player_role": {
        "id": 17,
        "position_group": "Other",
        "name": "Substitute",
        "acronym": "SUB"
      },
      "start_time": null,
      "end_time": null,
      "number": 50,
      "yellow_card": 0,
      "red_card": 0,
      "injured": false,
      "goal": 0,
      "own_goal": 0,
      "team_player_id": 1452035,
      "team_id": 89,
      "id": 926156,
      "first_name": "Noah ",
      "last_name": "Jauny",
      "short_name": "N. Jauny",
      "birthday": "2004-08-26",
      "trackable_object": 927719,
      "gender": "male"
    },
    {
      "player_role": {
        "id": 17,
        "position_group": "Other",
        "name": "Substitute",
        "acronym": "SUB"
      },
      "start_time": null,
      "end_time": null,
      "number": 25,
      "yellow_card": 0,
      "red_card": 0,
      "injured": false,
      "goal": 0,
      "own_goal": 0,
      "team_player_id": 1141299,
      "team_id": 89,
      "id": 39889,
      "first_name": "Julien",
      "last_name": "Le Cardinal",
      "short_name": "J. Le Cardinal",
      "birthday": "1997-08-03",
      "trackable_object": 41010,
      "gender": "male"
    },
    {
      "player_role": {
        "id": 17,
        "position_group": "Other",
        "name": "Substitute",
        "acronym": "SUB"
      },
      "start_time": null,
      "end_time": null,
      "number": 30,
      "yellow_card": 0,
      "red_card": 0,
      "injured": false,
      "goal": 0,
      "own_goal": 0,
      "team_player_id": 90259,
      "team_id": 89,
      "id": 33214,
      "first_name": "Grégoire",
      "last_name": "Coudert",
      "short_name": "G. Coudert",
      "birthday": "1999-04-03",
      "trackable_object": 34322,
      "gender": "male"
    },
    {
      "player_role": {
        "id": 17,
        "position_group": "Other",
        "name": "Substitute",
        "acronym": "SUB"
      },
      "start_time": null,
      "end_time": null,
      "number": 3,
      "yellow_card": 0,
      "red_card": 0,
      "injured": false,
      "goal": 0,
      "own_goal": 0,
      "team_player_id": 1441581,
      "team_id": 89,
      "id": 176523,
      "first_name": "Abdoulaye",
      "last_name": "Niakhate N'Diaye",
      "short_name": "A. N'Diaye",
      "birthday": "2002-04-10",
      "trackable_object": 178078,
      "gender": "male"
    },
    {
      "player_role": {
        "id": 3,
        "position_group": "Central Defender",
        "name": "Left Center Back",
        "acronym": "LCB"
      },
      "start_time": "00:00:00",
      "end_time": null,
      "number": 44,
      "yellow_card": 0,
      "red_card": 0,
      "injured": false,
      "goal": 0,
      "own_goal": 0,
      "team_player_id": 1414468,
      "team_id": 89,
      "id": 70850,
      "first_name": "Soumaïla",
      "last_name": "Coulibaly ",
      "short_name": "S. Coulibaly",
      "birthday": "2003-10-14",
      "trackable_object": 71976,
      "gender": "male"
    },
    {
      "player_role": {
        "id": 19,
        "position_group": "Full Back",
        "name": "Left Back",
        "acronym": "LB"
      },
      "start_time": "00:00:00",
      "end_time": null,
      "number": 26,
      "yellow_card": 1,
      "red_card": 0,
      "injured": false,
      "goal": 0,
      "own_goal": 0,
      "team_player_id": 240886,
      "team_id": 89,
      "id": 11336,
      "first_name": "Mathias",
      "last_name": "Pereira Lage",
      "short_name": "M. Pereira Lage",
      "birthday": "1996-11-30",
      "trackable_object": 11377,
      "gender": "male"
    },
    {
      "player_role": {
        "id": 0,
        "position_group": "Other",
        "name": "Goalkeeper",
        "acronym": "GK"
      },
      "start_time": "00:00:00",
      "end_time": null,
      "number": 40,
      "yellow_card": 0,
      "red_card": 0,
      "injured": false,
      "goal": 0,
      "own_goal": 0,
      "team_player_id": 90257,
      "team_id": 89,
      "id": 6756,
      "first_name": "Marco",
      "last_name": "Bizot",
      "short_name": "M. Bizot",
      "birthday": "1991-03-10",
      "trackable_object": 6766,
      "gender": "male"
    },
    {
      "player_role": {
        "id": 20,
        "position_group": "Full Back",
        "name": "Right Back",
        "acronym": "RB"
      },
      "start_time": "00:00:00",
      "end_time": null,
      "number": 7,
      "yellow_card": 0,
      "red_card": 0,
      "injured": false,
      "goal": 0,
      "own_goal": 0,
      "team_player_id": 753269,
      "team_id": 89,
      "id": 5789,
      "first_name": "Kenny",
      "last_name": "Lala",
      "short_name": "K. Lala",
      "birthday": "1991-10-03",
      "trackable_object": 5799,
      "gender": "male"
    },
    {
      "player_role": {
        "id": 7,
        "position_group": "Midfield",
        "name": "Defensive Midfield",
        "acronym": "DM"
      },
      "start_time": "00:00:00",
      "end_time": null,
      "number": 6,
      "yellow_card": 0,
      "red_card": 0,
      "injured": false,
      "goal": 0,
      "own_goal": 0,
      "team_player_id": 1441579,
      "team_id": 89,
      "id": 13030,
      "first_name": "Edimilson",
      "last_name": "Fernandes Ribeiro",
      "short_name": "E. Fernandes",
      "birthday": "1996-04-15",
      "trackable_object": 13209,
      "gender": "male"
    },
    {
      "player_role": {
        "id": 4,
        "position_group": "Central Defender",
        "name": "Right Center Back",
        "acronym": "RCB"
      },
      "start_time": "00:00:00",
      "end_time": null,
      "number": 5,
      "yellow_card": 0,
      "red_card": 0,
      "injured": false,
      "goal": 0,
      "own_goal": 0,
      "team_player_id": 8405,
      "team_id": 89,
      "id": 13164,
      "first_name": "Brendan",
      "last_name": "Chardonnet",
      "short_name": "B. Chardonnet",
      "birthday": "1994-12-22",
      "trackable_object": 13348,
      "gender": "male"
    }
  ],
  "status": "closed",
  "home_team_side": [
    "right_to_left",
    "left_to_right"
  ],
  "ball": {
    "trackable_object": 55
  },
  "pitch_length": 105,
  "pitch_width": 68
}